dagster_sqlmesh/__init__.py
dagster_sqlmesh/asset.py
dagster_sqlmesh/config.py
dagster_sqlmesh/conftest.py
dagster_sqlmesh/console.py
dagster_sqlmesh/events.py
dagster_sqlmesh/py.typed
dagster_sqlmesh/resource.py
dagster_sqlmesh/scheduler.py
dagster_sqlmesh/test_asset.py
dagster_sqlmesh/test_resource.py
dagster_sqlmesh/test_sqlmesh_context.py
dagster_sqlmesh/translator.py
dagster_sqlmesh/types.py
dagster_sqlmesh/utils.py
dagster_sqlmesh/controller/__init__.py
dagster_sqlmesh/controller/base.py
dagster_sqlmesh/controller/dagster.py
dagster_sqlmesh/testing/__init__.py
dagster_sqlmesh/testing/context.py
dagster_sqlmesh-0.22.0.dist-info/METADATA
dagster_sqlmesh-0.22.0.dist-info/WHEEL
dagster_sqlmesh-0.22.0.dist-info/licenses/LICENSE
dagster_sqlmesh-0.22.0.dist-info/RECORD
