Metadata-Version: 2.4
Name: dagster-sqlmesh
Version: 0.22.0
Author-email: Reuven Gonzales <reuven@karibalabs.co>
License: Apache-2.0
License-File: LICENSE
Requires-Python: <3.13,>=3.11
Requires-Dist: dagster>=1.7.8
Requires-Dist: pyarrow>=18.0.0
Requires-Dist: pydantic>=2.11.5
Requires-Dist: pytest>=8.3.2
Requires-Dist: sqlmesh>=0.188
